py4byte/__init__.py
py4byte/api.py
py4byte/meta.py
py4byte-0.1.5.dist-info/LICENSE
py4byte-0.1.5.dist-info/METADATA
py4byte-0.1.5.dist-info/WHEEL
py4byte-0.1.5.dist-info/top_level.txt
py4byte-0.1.5.dist-info/RECORD
