Metadata-Version: 2.1
Name: py4byte
Version: 0.1.5
Summary: Python library that leverages the 4byte.directory
Home-page: https://github.com/mikeshultz/py4byte
Author: Mike Shultz
Author-email: shultzm@gmail.com
License: UNKNOWN
Keywords: ethereum blockchain topic function event signature 4byte
Platform: UNKNOWN
Classifier: Development Status :: 3 - Alpha
Classifier: Intended Audience :: Developers
Classifier: License :: OSI Approved :: MIT License
Classifier: Programming Language :: Python :: 3
Classifier: Programming Language :: Python :: 3.6
Classifier: Programming Language :: Python :: 3.7
Classifier: Programming Language :: Python :: 3.8
Requires-Dist: requests (>=2.25.0)
